{"ongoing_trials": {"tuner0": "0012"}, "hyperparameters": {"space": [{"class_name": "Int", "config": {"name": "input_unit", "default": null, "conditions": [], "min_value": 32, "max_value": 512, "step": 32, "sampling": null}}, {"class_name": "Int", "config": {"name": "n_layers", "default": null, "conditions": [], "min_value": 1, "max_value": 5, "step": 1, "sampling": null}}, {"class_name": "Int", "config": {"name": "dense_0_units", "default": null, "conditions": [], "min_value": 32, "max_value": 512, "step": 32, "sampling": null}}, {"class_name": "Float", "config": {"name": "dropout_rate", "default": 0.0, "conditions": [], "min_value": 0.0, "max_value": 0.5, "step": 0.1, "sampling": null}}, {"class_name": "Choice", "config": {"name": "learning_rate", "default": 0.1, "conditions": [], "values": [0.1, 0.01, 0.001, 0.0001], "ordered": true}}, {"class_name": "Int", "config": {"name": "dense_1_units", "default": null, "conditions": [], "min_value": 32, "max_value": 512, "step": 32, "sampling": null}}, {"class_name": "Int", "config": {"name": "dense_2_units", "default": null, "conditions": [], "min_value": 32, "max_value": 512, "step": 32, "sampling": null}}, {"class_name": "Int", "config": {"name": "dense_3_units", "default": null, "conditions": [], "min_value": 32, "max_value": 512, "step": 32, "sampling": null}}, {"class_name": "Int", "config": {"name": "dense_4_units", "default": null, "conditions": [], "min_value": 32, "max_value": 512, "step": 32, "sampling": null}}], "values": {"input_unit": 32, "n_layers": 1, "dense_0_units": 32, "dropout_rate": 0.0, "learning_rate": 0.1, "dense_1_units": 32, "dense_2_units": 32, "dense_3_units": 32, "dense_4_units": 32}}, "seed": 3568, "seed_state": 3679, "tried_so_far": ["a63d2c14fe2a71c44423df19c4f4554e", "f6bd5af6e8f55741fff0ef4eaa323149", "a038a6f0588cf12c6dc984205569a454", "b069c97e4d4dda4c83f061ad4017d61a", "ad385a519f0205d42dec5e234005c947", "3d041b15b55f3c18a45d14fba15eebe1", "9079dbf99bac2a7d99a2bfd938462bbd", "8e1ac409d2ea53b909248dc317fdf93d", "f4da61dd1a9a6d1b623d69c4ab806a00", "fee0d4224140b2694673146f52d9ea4d", "907700fa7784fab16608faaee499d01f", "77695efcf645c6c47452e37092e21673", "c2acfbaed0ff63d3e8cc4a2ff977e939"], "hyperband_iterations": 1, "max_epochs": 50, "min_epochs": 1, "factor": 3, "brackets": [{"bracket_num": 3, "rounds": [[{"past_id": null, "id": "0000"}, {"past_id": null, "id": "0001"}, {"past_id": null, "id": "0002"}, {"past_id": null, "id": "0003"}, {"past_id": null, "id": "0004"}, {"past_id": null, "id": "0005"}, {"past_id": null, "id": "0006"}, {"past_id": null, "id": "0007"}, {"past_id": null, "id": "0008"}, {"past_id": null, "id": "0009"}, {"past_id": null, "id": "0010"}, {"past_id": null, "id": "0011"}, {"past_id": null, "id": "0012"}], [], [], []]}], "current_bracket": 3, "current_iteration": 0}